ssnappyweb/__init__.py
ssnappyweb/__main__.py
ssnappyweb/main.py
ssnappyweb-0.1.1.dist-info/METADATA
ssnappyweb-0.1.1.dist-info/WHEEL
ssnappyweb-0.1.1.dist-info/entry_points.txt
ssnappyweb-0.1.1.dist-info/top_level.txt
ssnappyweb-0.1.1.dist-info/RECORD
