Metadata-Version: 2.4
Name: ssnappyweb
Version: 0.1.1
Requires-Dist: cryptography
Dynamic: requires-dist
